[
  {
    "name": "左奇函",
    "id": "60705549",
    "today_gift": 61314,
    "today_users": 1470,
    "avg": 41.71,
    "total_gift": 12877563,
    "status": "成功"
  },
  {
    "name": "张函瑞",
    "id": "64761230",
    "today_gift": 81799,
    "today_users": 2474,
    "avg": 33.06,
    "total_gift": 24214814,
    "status": "成功"
  },
  {
    "name": "张桂源",
    "id": "64767448",
    "today_gift": 73127,
    "today_users": 2004,
    "avg": 36.49,
    "total_gift": 14808986,
    "status": "成功"
  },
  {
    "name": "陈奕恒",
    "id": "64786973",
    "today_gift": 96456,
    "today_users": 2702,
    "avg": 35.7,
    "total_gift": 13890508,
    "status": "成功"
  },
  {
    "name": "王橹杰",
    "id": "64787018",
    "today_gift": 205241,
    "today_users": 4206,
    "avg": 48.8,
    "total_gift": 37540572,
    "status": "成功"
  },
  {
    "name": "陈浚铭",
    "id": "64762675",
    "today_gift": 93090,
    "today_users": 2898,
    "avg": 32.12,
    "total_gift": 17979188,
    "status": "成功"
  },
  {
    "name": "杨博文",
    "id": "64790097",
    "today_gift": 105245,
    "today_users": 3014,
    "avg": 34.92,
    "total_gift": 26597079,
    "status": "成功"
  }
]