[
  {
    "name": "张桂源",
    "id": "64767448",
    "today_gift": 18557,
    "today_users": 738,
    "avg": 25.14,
    "total_gift": 10695453,
    "status": "成功"
  },
  {
    "name": "王橹杰",
    "id": "64787018",
    "today_gift": 36421,
    "today_users": 1654,
    "avg": 22.02,
    "total_gift": 27656089,
    "status": "成功"
  },
  {
    "name": "左奇函",
    "id": "60705549",
    "today_gift": 11518,
    "today_users": 821,
    "avg": 14.03,
    "total_gift": 9286539,
    "status": "成功"
  },
  {
    "name": "陈奕恒",
    "id": "64786973",
    "today_gift": 23402,
    "today_users": 1212,
    "avg": 19.31,
    "total_gift": 9504648,
    "status": "成功"
  },
  {
    "name": "张函瑞",
    "id": "64761230",
    "today_gift": 31402,
    "today_users": 1446,
    "avg": 21.72,
    "total_gift": 18540332,
    "status": "成功"
  },
  {
    "name": "陈浚铭",
    "id": "64762675",
    "today_gift": 21159,
    "today_users": 1045,
    "avg": 20.25,
    "total_gift": 13115277,
    "status": "成功"
  },
  {
    "name": "杨博文",
    "id": "64790097",
    "today_gift": 17130,
    "today_users": 1162,
    "avg": 14.74,
    "total_gift": 20646644,
    "status": "成功"
  }
]