[
  {
    "name": "陈奕恒",
    "id": "64786973",
    "today_gift": 60692,
    "today_users": 2538,
    "avg": 23.91,
    "total_gift": 11818130,
    "status": "成功"
  },
  {
    "name": "左奇函",
    "id": "60705549",
    "today_gift": 32950,
    "today_users": 1539,
    "avg": 21.41,
    "total_gift": 11327122,
    "status": "成功"
  },
  {
    "name": "张桂源",
    "id": "64767448",
    "today_gift": 49384,
    "today_users": 2292,
    "avg": 21.55,
    "total_gift": 13070810,
    "status": "成功"
  },
  {
    "name": "王橹杰",
    "id": "64787018",
    "today_gift": 102215,
    "today_users": 3916,
    "avg": 26.1,
    "total_gift": 32593832,
    "status": "成功"
  },
  {
    "name": "张函瑞",
    "id": "64761230",
    "today_gift": 59063,
    "today_users": 2661,
    "avg": 22.2,
    "total_gift": 21811652,
    "status": "成功"
  },
  {
    "name": "杨博文",
    "id": "64790097",
    "today_gift": 59842,
    "today_users": 3249,
    "avg": 18.42,
    "total_gift": 23977887,
    "status": "成功"
  },
  {
    "name": "陈浚铭",
    "id": "64762675",
    "today_gift": 50820,
    "today_users": 2586,
    "avg": 19.65,
    "total_gift": 15691090,
    "status": "成功"
  }
]