[
  {
    "name": "张函瑞",
    "id": "64761230",
    "today_gift": 134047,
    "today_users": 3994,
    "avg": 33.56,
    "total_gift": 21886636,
    "status": "成功"
  },
  {
    "name": "张桂源",
    "id": "64767448",
    "today_gift": 103257,
    "today_users": 3431,
    "avg": 30.1,
    "total_gift": 13124683,
    "status": "成功"
  },
  {
    "name": "左奇函",
    "id": "60705549",
    "today_gift": 87612,
    "today_users": 2265,
    "avg": 38.68,
    "total_gift": 11381784,
    "status": "成功"
  },
  {
    "name": "陈奕恒",
    "id": "64786973",
    "today_gift": 106387,
    "today_users": 3657,
    "avg": 29.09,
    "total_gift": 11863825,
    "status": "成功"
  },
  {
    "name": "王橹杰",
    "id": "64787018",
    "today_gift": 239697,
    "today_users": 6304,
    "avg": 38.02,
    "total_gift": 32731312,
    "status": "成功"
  },
  {
    "name": "陈浚铭",
    "id": "64762675",
    "today_gift": 112026,
    "today_users": 3907,
    "avg": 28.67,
    "total_gift": 15752296,
    "status": "成功"
  },
  {
    "name": "杨博文",
    "id": "64790097",
    "today_gift": 135191,
    "today_users": 4724,
    "avg": 28.62,
    "total_gift": 24053236,
    "status": "成功"
  }
]