[
  {
    "name": "王橹杰",
    "id": "64787018",
    "today_gift": 20086,
    "today_users": 1004,
    "avg": 20.01,
    "total_gift": 31460094,
    "status": "成功"
  },
  {
    "name": "左奇函",
    "id": "60705549",
    "today_gift": 5253,
    "today_users": 405,
    "avg": 12.97,
    "total_gift": 10925504,
    "status": "成功"
  },
  {
    "name": "张函瑞",
    "id": "64761230",
    "today_gift": 15697,
    "today_users": 622,
    "avg": 25.24,
    "total_gift": 21132407,
    "status": "成功"
  },
  {
    "name": "陈奕恒",
    "id": "64786973",
    "today_gift": 11577,
    "today_users": 471,
    "avg": 24.58,
    "total_gift": 11319592,
    "status": "成功"
  },
  {
    "name": "张桂源",
    "id": "64767448",
    "today_gift": 8779,
    "today_users": 415,
    "avg": 21.15,
    "total_gift": 12564677,
    "status": "成功"
  },
  {
    "name": "杨博文",
    "id": "64790097",
    "today_gift": 9683,
    "today_users": 592,
    "avg": 16.36,
    "total_gift": 23281297,
    "status": "成功"
  },
  {
    "name": "陈浚铭",
    "id": "64762675",
    "today_gift": 9296,
    "today_users": 463,
    "avg": 20.08,
    "total_gift": 15144613,
    "status": "成功"
  }
]