[
  {
    "name": "张函瑞",
    "id": "64761230",
    "today_gift": 136901,
    "today_users": 4236,
    "avg": 32.32,
    "total_gift": 21076210,
    "status": "成功"
  },
  {
    "name": "左奇函",
    "id": "60705549",
    "today_gift": 92450,
    "today_users": 2452,
    "avg": 37.7,
    "total_gift": 10905161,
    "status": "成功"
  },
  {
    "name": "陈奕恒",
    "id": "64786973",
    "today_gift": 100284,
    "today_users": 3836,
    "avg": 26.14,
    "total_gift": 11294440,
    "status": "成功"
  },
  {
    "name": "张桂源",
    "id": "64767448",
    "today_gift": 107946,
    "today_users": 3854,
    "avg": 28.01,
    "total_gift": 12538471,
    "status": "成功"
  },
  {
    "name": "王橹杰",
    "id": "64787018",
    "today_gift": 234800,
    "today_users": 5754,
    "avg": 40.81,
    "total_gift": 31391621,
    "status": "成功"
  },
  {
    "name": "陈浚铭",
    "id": "64762675",
    "today_gift": 111852,
    "today_users": 3480,
    "avg": 32.14,
    "total_gift": 15118171,
    "status": "成功"
  },
  {
    "name": "杨博文",
    "id": "64790097",
    "today_gift": 137798,
    "today_users": 5262,
    "avg": 26.19,
    "total_gift": 23236366,
    "status": "成功"
  }
]