[
  {
    "name": "陈奕恒",
    "id": "64786973",
    "today_gift": 27961,
    "today_users": 700,
    "avg": 39.94,
    "total_gift": 13822012,
    "status": "成功"
  },
  {
    "name": "张函瑞",
    "id": "64761230",
    "today_gift": 21903,
    "today_users": 611,
    "avg": 35.85,
    "total_gift": 24154918,
    "status": "成功"
  },
  {
    "name": "张桂源",
    "id": "64767448",
    "today_gift": 20599,
    "today_users": 547,
    "avg": 37.66,
    "total_gift": 14756458,
    "status": "成功"
  },
  {
    "name": "左奇函",
    "id": "60705549",
    "today_gift": 12683,
    "today_users": 460,
    "avg": 27.57,
    "total_gift": 12828932,
    "status": "成功"
  },
  {
    "name": "王橹杰",
    "id": "64787018",
    "today_gift": 54834,
    "today_users": 1366,
    "avg": 40.14,
    "total_gift": 37390165,
    "status": "成功"
  },
  {
    "name": "陈浚铭",
    "id": "64762675",
    "today_gift": 24252,
    "today_users": 893,
    "avg": 27.16,
    "total_gift": 17910350,
    "status": "成功"
  },
  {
    "name": "杨博文",
    "id": "64790097",
    "today_gift": 25526,
    "today_users": 709,
    "avg": 36.0,
    "total_gift": 26517360,
    "status": "成功"
  }
]