[
  {
    "name": "王橹杰",
    "id": "64787018",
    "today_gift": 110244,
    "today_users": 3384,
    "avg": 32.58,
    "total_gift": 31833942,
    "status": "成功"
  },
  {
    "name": "张桂源",
    "id": "64767448",
    "today_gift": 58540,
    "today_users": 2431,
    "avg": 24.08,
    "total_gift": 12736524,
    "status": "成功"
  },
  {
    "name": "左奇函",
    "id": "60705549",
    "today_gift": 37309,
    "today_users": 1558,
    "avg": 23.95,
    "total_gift": 11058812,
    "status": "成功"
  },
  {
    "name": "陈奕恒",
    "id": "64786973",
    "today_gift": 59495,
    "today_users": 2323,
    "avg": 25.61,
    "total_gift": 11483938,
    "status": "成功"
  },
  {
    "name": "张函瑞",
    "id": "64761230",
    "today_gift": 65866,
    "today_users": 2764,
    "avg": 23.83,
    "total_gift": 21356213,
    "status": "成功"
  },
  {
    "name": "陈浚铭",
    "id": "64762675",
    "today_gift": 58789,
    "today_users": 2544,
    "avg": 23.11,
    "total_gift": 15321586,
    "status": "成功"
  },
  {
    "name": "杨博文",
    "id": "64790097",
    "today_gift": 64508,
    "today_users": 3049,
    "avg": 21.16,
    "total_gift": 23506664,
    "status": "成功"
  }
]