[
  {
    "name": "左奇函",
    "id": "60705549",
    "today_gift": 13923,
    "today_users": 786,
    "avg": 17.71,
    "total_gift": 8760981,
    "status": "成功"
  },
  {
    "name": "王橹杰",
    "id": "64787018",
    "today_gift": 36208,
    "today_users": 1605,
    "avg": 22.56,
    "total_gift": 26439801,
    "status": "成功"
  },
  {
    "name": "张桂源",
    "id": "64767448",
    "today_gift": 24951,
    "today_users": 821,
    "avg": 30.39,
    "total_gift": 10173997,
    "status": "成功"
  },
  {
    "name": "陈奕恒",
    "id": "64786973",
    "today_gift": 23790,
    "today_users": 1151,
    "avg": 20.67,
    "total_gift": 8918043,
    "status": "成功"
  },
  {
    "name": "张函瑞",
    "id": "64761230",
    "today_gift": 21389,
    "today_users": 1096,
    "avg": 19.52,
    "total_gift": 17732468,
    "status": "成功"
  },
  {
    "name": "陈浚铭",
    "id": "64762675",
    "today_gift": 18431,
    "today_users": 915,
    "avg": 20.14,
    "total_gift": 12464821,
    "status": "成功"
  },
  {
    "name": "杨博文",
    "id": "64790097",
    "today_gift": 18196,
    "today_users": 1188,
    "avg": 15.32,
    "total_gift": 19827561,
    "status": "成功"
  }
]