[
  {
    "name": "王橹杰",
    "id": "64787018",
    "today_gift": 286183,
    "today_users": 6867,
    "avg": 41.68,
    "total_gift": 38342034,
    "status": "成功"
  },
  {
    "name": "陈奕恒",
    "id": "64786973",
    "today_gift": 113712,
    "today_users": 3721,
    "avg": 30.56,
    "total_gift": 14184214,
    "status": "成功"
  },
  {
    "name": "左奇函",
    "id": "60705549",
    "today_gift": 75340,
    "today_users": 1965,
    "avg": 38.34,
    "total_gift": 13097526,
    "status": "成功"
  },
  {
    "name": "张函瑞",
    "id": "64761230",
    "today_gift": 102665,
    "today_users": 3416,
    "avg": 30.05,
    "total_gift": 24560413,
    "status": "成功"
  },
  {
    "name": "张桂源",
    "id": "64767448",
    "today_gift": 88068,
    "today_users": 2768,
    "avg": 31.82,
    "total_gift": 15056789,
    "status": "成功"
  },
  {
    "name": "陈浚铭",
    "id": "64762675",
    "today_gift": 133980,
    "today_users": 4343,
    "avg": 30.85,
    "total_gift": 18317965,
    "status": "成功"
  },
  {
    "name": "杨博文",
    "id": "64790097",
    "today_gift": 148265,
    "today_users": 4206,
    "avg": 35.25,
    "total_gift": 26981760,
    "status": "成功"
  }
]