[
  {
    "name": "左奇函",
    "id": "60705549",
    "today_gift": 36370,
    "today_users": 1431,
    "avg": 25.42,
    "total_gift": 12968856,
    "status": "成功"
  },
  {
    "name": "陈奕恒",
    "id": "64786973",
    "today_gift": 69688,
    "today_users": 2849,
    "avg": 24.46,
    "total_gift": 14020408,
    "status": "成功"
  },
  {
    "name": "张桂源",
    "id": "64767448",
    "today_gift": 42141,
    "today_users": 1925,
    "avg": 21.89,
    "total_gift": 14911128,
    "status": "成功"
  },
  {
    "name": "王橹杰",
    "id": "64787018",
    "today_gift": 130387,
    "today_users": 4220,
    "avg": 30.9,
    "total_gift": 37886825,
    "status": "成功"
  },
  {
    "name": "张函瑞",
    "id": "64761230",
    "today_gift": 43774,
    "today_users": 2099,
    "avg": 20.85,
    "total_gift": 24345785,
    "status": "成功"
  },
  {
    "name": "陈浚铭",
    "id": "64762675",
    "today_gift": 56987,
    "today_users": 2453,
    "avg": 23.23,
    "total_gift": 18110492,
    "status": "成功"
  },
  {
    "name": "杨博文",
    "id": "64790097",
    "today_gift": 62278,
    "today_users": 2973,
    "avg": 20.95,
    "total_gift": 26745083,
    "status": "成功"
  }
]