[
  {
    "name": "张桂源",
    "id": "64767448",
    "today_gift": 82560,
    "today_users": 2717,
    "avg": 30.39,
    "total_gift": 9943323,
    "status": "成功"
  },
  {
    "name": "左奇函",
    "id": "60705549",
    "today_gift": 66667,
    "today_users": 2152,
    "avg": 30.98,
    "total_gift": 8545382,
    "status": "成功"
  },
  {
    "name": "张函瑞",
    "id": "64761230",
    "today_gift": 107607,
    "today_users": 4045,
    "avg": 26.6,
    "total_gift": 17392523,
    "status": "成功"
  },
  {
    "name": "陈奕恒",
    "id": "64786973",
    "today_gift": 101873,
    "today_users": 3678,
    "avg": 27.7,
    "total_gift": 8689141,
    "status": "成功"
  },
  {
    "name": "王橹杰",
    "id": "64787018",
    "today_gift": 160499,
    "today_users": 4483,
    "avg": 35.8,
    "total_gift": 25913026,
    "status": "成功"
  },
  {
    "name": "杨博文",
    "id": "64790097",
    "today_gift": 110524,
    "today_users": 3968,
    "avg": 27.85,
    "total_gift": 19471873,
    "status": "成功"
  },
  {
    "name": "陈浚铭",
    "id": "64762675",
    "today_gift": 95339,
    "today_users": 2980,
    "avg": 31.99,
    "total_gift": 12218078,
    "status": "成功"
  }
]