[
  {
    "name": "张桂源",
    "id": "64767448",
    "today_gift": 15469,
    "today_users": 795,
    "avg": 19.46,
    "total_gift": 13760089,
    "status": "成功"
  },
  {
    "name": "左奇函",
    "id": "60705549",
    "today_gift": 10494,
    "today_users": 672,
    "avg": 15.62,
    "total_gift": 11933876,
    "status": "成功"
  },
  {
    "name": "王橹杰",
    "id": "64787018",
    "today_gift": 39478,
    "today_users": 1670,
    "avg": 23.64,
    "total_gift": 34347707,
    "status": "成功"
  },
  {
    "name": "陈奕恒",
    "id": "64786973",
    "today_gift": 20725,
    "today_users": 1150,
    "avg": 18.02,
    "total_gift": 12616354,
    "status": "成功"
  },
  {
    "name": "张函瑞",
    "id": "64761230",
    "today_gift": 16075,
    "today_users": 928,
    "avg": 17.32,
    "total_gift": 22721208,
    "status": "成功"
  },
  {
    "name": "陈浚铭",
    "id": "64762675",
    "today_gift": 13664,
    "today_users": 862,
    "avg": 15.85,
    "total_gift": 16470023,
    "status": "成功"
  },
  {
    "name": "杨博文",
    "id": "64790097",
    "today_gift": 14215,
    "today_users": 1106,
    "avg": 12.85,
    "total_gift": 24933429,
    "status": "成功"
  }
]