[
  {
    "name": "左奇函",
    "id": "60705549",
    "today_gift": 10134,
    "today_users": 586,
    "avg": 17.29,
    "total_gift": 9906974,
    "status": "成功"
  },
  {
    "name": "张函瑞",
    "id": "64761230",
    "today_gift": 16891,
    "today_users": 738,
    "avg": 22.89,
    "total_gift": 19477396,
    "status": "成功"
  },
  {
    "name": "王橹杰",
    "id": "64787018",
    "today_gift": 23915,
    "today_users": 1160,
    "avg": 20.62,
    "total_gift": 29073764,
    "status": "成功"
  },
  {
    "name": "陈奕恒",
    "id": "64786973",
    "today_gift": 17325,
    "today_users": 739,
    "avg": 23.44,
    "total_gift": 10168014,
    "status": "成功"
  },
  {
    "name": "张桂源",
    "id": "64767448",
    "today_gift": 9995,
    "today_users": 473,
    "avg": 21.13,
    "total_gift": 11285926,
    "status": "成功"
  },
  {
    "name": "陈浚铭",
    "id": "64762675",
    "today_gift": 16169,
    "today_users": 704,
    "avg": 22.97,
    "total_gift": 13841960,
    "status": "成功"
  },
  {
    "name": "杨博文",
    "id": "64790097",
    "today_gift": 15417,
    "today_users": 810,
    "avg": 19.03,
    "total_gift": 21603530,
    "status": "成功"
  }
]