[
  {
    "name": "张桂源",
    "id": "64767448",
    "today_gift": 29339,
    "today_users": 912,
    "avg": 32.17,
    "total_gift": 11605947,
    "status": "成功"
  },
  {
    "name": "左奇函",
    "id": "60705549",
    "today_gift": 8146,
    "today_users": 504,
    "avg": 16.16,
    "total_gift": 10144959,
    "status": "成功"
  },
  {
    "name": "张函瑞",
    "id": "64761230",
    "today_gift": 26112,
    "today_users": 953,
    "avg": 27.4,
    "total_gift": 19853650,
    "status": "成功"
  },
  {
    "name": "王橹杰",
    "id": "64787018",
    "today_gift": 31933,
    "today_users": 1269,
    "avg": 25.16,
    "total_gift": 29622583,
    "status": "成功"
  },
  {
    "name": "陈奕恒",
    "id": "64786973",
    "today_gift": 13306,
    "today_users": 656,
    "avg": 20.28,
    "total_gift": 10428336,
    "status": "成功"
  },
  {
    "name": "陈浚铭",
    "id": "64762675",
    "today_gift": 17557,
    "today_users": 764,
    "avg": 22.98,
    "total_gift": 14136045,
    "status": "成功"
  },
  {
    "name": "杨博文",
    "id": "64790097",
    "today_gift": 10230,
    "today_users": 736,
    "avg": 13.9,
    "total_gift": 21938038,
    "status": "成功"
  }
]