[
  {
    "name": "陈奕恒",
    "id": "64786973",
    "today_gift": 47140,
    "today_users": 2228,
    "avg": 21.16,
    "total_gift": 11241296,
    "status": "成功"
  },
  {
    "name": "左奇函",
    "id": "60705549",
    "today_gift": 30004,
    "today_users": 1504,
    "avg": 19.95,
    "total_gift": 10842714,
    "status": "成功"
  },
  {
    "name": "张函瑞",
    "id": "64761230",
    "today_gift": 48301,
    "today_users": 2263,
    "avg": 21.34,
    "total_gift": 20987610,
    "status": "成功"
  },
  {
    "name": "张桂源",
    "id": "64767448",
    "today_gift": 46595,
    "today_users": 2171,
    "avg": 21.46,
    "total_gift": 12477120,
    "status": "成功"
  },
  {
    "name": "王橹杰",
    "id": "64787018",
    "today_gift": 75905,
    "today_users": 2819,
    "avg": 26.93,
    "total_gift": 31232727,
    "status": "成功"
  },
  {
    "name": "陈浚铭",
    "id": "64762675",
    "today_gift": 40584,
    "today_users": 1914,
    "avg": 21.2,
    "total_gift": 15046903,
    "status": "成功"
  },
  {
    "name": "杨博文",
    "id": "64790097",
    "today_gift": 45319,
    "today_users": 2834,
    "avg": 15.99,
    "total_gift": 23143887,
    "status": "成功"
  }
]