[
  {
    "name": "左奇函",
    "id": "60705549",
    "today_gift": 57102,
    "today_users": 1915,
    "avg": 29.82,
    "total_gift": 10537094,
    "status": "成功"
  },
  {
    "name": "张函瑞",
    "id": "64761230",
    "today_gift": 96593,
    "today_users": 3577,
    "avg": 27.0,
    "total_gift": 20519405,
    "status": "成功"
  },
  {
    "name": "王橹杰",
    "id": "64787018",
    "today_gift": 136776,
    "today_users": 4012,
    "avg": 34.09,
    "total_gift": 30542197,
    "status": "成功"
  },
  {
    "name": "陈奕恒",
    "id": "64786973",
    "today_gift": 82045,
    "today_users": 3094,
    "avg": 26.52,
    "total_gift": 10896523,
    "status": "成功"
  },
  {
    "name": "张桂源",
    "id": "64767448",
    "today_gift": 81515,
    "today_users": 3565,
    "avg": 22.87,
    "total_gift": 12115996,
    "status": "成功"
  },
  {
    "name": "陈浚铭",
    "id": "64762675",
    "today_gift": 81051,
    "today_users": 2886,
    "avg": 28.08,
    "total_gift": 14666697,
    "status": "成功"
  },
  {
    "name": "杨博文",
    "id": "64790097",
    "today_gift": 110445,
    "today_users": 4481,
    "avg": 24.65,
    "total_gift": 22639364,
    "status": "成功"
  }
]