{
  "date": "2026-06-29",
  "baseline": {
    "6353131515": {
      "comment": 46709845,
      "repost": 408999979,
      "like": 57621504,
      "total": 513331328
    },
    "7740929779": {
      "comment": 85270884,
      "repost": 648954904,
      "like": 57211394,
      "total": 791437182
    },
    "3625607515": {
      "comment": 28738388,
      "repost": 473227647,
      "like": 186542757,
      "total": 688508792
    },
    "3448351424": {
      "comment": 29997551,
      "repost": 182899425,
      "like": 52220231,
      "total": 265117207
    },
    "6320179782": {
      "comment": 53859266,
      "repost": 173851945,
      "like": 73536636,
      "total": 301247847
    },
    "7817162132": {
      "comment": 62566550,
      "repost": 389296007,
      "like": 80906994,
      "total": 532769551
    },
    "3177765082": {
      "comment": 17477877,
      "repost": 217067369,
      "like": 50683094,
      "total": 285228340
    }
  },
  "current": {
    "6353131515": {
      "comment": 46783749,
      "repost": 409768017,
      "like": 57649275,
      "total": 514201041,
      "followers": 2812567
    },
    "7740929779": {
      "comment": 85316139,
      "repost": 649767545,
      "like": 57271956,
      "total": 792355640,
      "followers": 2360900
    },
    "3625607515": {
      "comment": 28791020,
      "repost": 476887587,
      "like": 186588942,
      "total": 692267549,
      "followers": 3321394
    },
    "3448351424": {
      "comment": 30053665,
      "repost": 183019239,
      "like": 52260456,
      "total": 265333360,
      "followers": 2780034
    },
    "6320179782": {
      "comment": 53908230,
      "repost": 174275108,
      "like": 73597891,
      "total": 301781229,
      "followers": 2630519
    },
    "7817162132": {
      "comment": 62719748,
      "repost": 389894616,
      "like": 80987845,
      "total": 533602209,
      "followers": 2786906
    },
    "3177765082": {
      "comment": 17537345,
      "repost": 217363921,
      "like": 50712133,
      "total": 285613399,
      "followers": 2819484
    }
  },
  "update_time": "2026-06-29 22:39:14"
}