{
  "date": "2026-06-22",
  "baseline": {
    "6353131515": {
      "comment": 46169147,
      "repost": 401531036,
      "like": 56402123,
      "total": 504102306
    },
    "7740929779": {
      "comment": 84723626,
      "repost": 642796326,
      "like": 56357346,
      "total": 783877298
    },
    "3625607515": {
      "comment": 28194351,
      "repost": 437035764,
      "like": 183167533,
      "total": 648397648
    },
    "3448351424": {
      "comment": 29447243,
      "repost": 181618512,
      "like": 51064856,
      "total": 262130611
    },
    "6320179782": {
      "comment": 53336270,
      "repost": 169955992,
      "like": 72285475,
      "total": 295577737
    },
    "7817162132": {
      "comment": 61403369,
      "repost": 384289402,
      "like": 79435892,
      "total": 525128663
    },
    "3177765082": {
      "comment": 16812161,
      "repost": 213647831,
      "like": 49324039,
      "total": 279784031
    }
  },
  "current": {
    "6353131515": {
      "comment": 46218404,
      "repost": 402102046,
      "like": 56518750,
      "total": 504839200,
      "followers": 2793045
    },
    "7740929779": {
      "comment": 84769387,
      "repost": 643414074,
      "like": 56371948,
      "total": 784555409,
      "followers": 2354150
    },
    "3625607515": {
      "comment": 28211933,
      "repost": 439491800,
      "like": 183238384,
      "total": 650942117,
      "followers": 3290791
    },
    "3448351424": {
      "comment": 29474200,
      "repost": 181700822,
      "like": 51106767,
      "total": 262281789,
      "followers": 2754587
    },
    "6320179782": {
      "comment": 53359981,
      "repost": 170254200,
      "like": 72315765,
      "total": 295929946,
      "followers": 2597442
    },
    "7817162132": {
      "comment": 61478129,
      "repost": 384613380,
      "like": 79477718,
      "total": 525569227,
      "followers": 2762728
    },
    "3177765082": {
      "comment": 16844484,
      "repost": 213830468,
      "like": 49373604,
      "total": 280048556,
      "followers": 2795427
    }
  },
  "update_time": "2026-06-22 10:30:52"
}