{
  "date": "2026-07-11",
  "baseline": {
    "6353131515": {
      "comment": 47634805,
      "repost": 420793443,
      "like": 58558344,
      "total": 526986592
    },
    "7740929779": {
      "comment": 85887172,
      "repost": 657732781,
      "like": 58179862,
      "total": 801799815
    },
    "3625607515": {
      "comment": 29661357,
      "repost": 541577114,
      "like": 193516553,
      "total": 764755024
    },
    "3448351424": {
      "comment": 30713207,
      "repost": 184902517,
      "like": 53747619,
      "total": 269363343
    },
    "6320179782": {
      "comment": 54878579,
      "repost": 180393887,
      "like": 75993501,
      "total": 311265967
    },
    "7817162132": {
      "comment": 64636599,
      "repost": 399004023,
      "like": 83669797,
      "total": 547310419
    },
    "3177765082": {
      "comment": 18415345,
      "repost": 223000668,
      "like": 53257146,
      "total": 294673159
    }
  },
  "current": {
    "6353131515": {
      "comment": 47693266,
      "repost": 421596209,
      "like": 58582349,
      "total": 527871824,
      "followers": 2866320
    },
    "7740929779": {
      "comment": 85919576,
      "repost": 658216360,
      "like": 58210380,
      "total": 802346316,
      "followers": 2375239
    },
    "3625607515": {
      "comment": 29690806,
      "repost": 545698615,
      "like": 193617281,
      "total": 769006702,
      "followers": 3369295
    },
    "3448351424": {
      "comment": 30775544,
      "repost": 185060847,
      "like": 53994614,
      "total": 269831005,
      "followers": 2836952
    },
    "6320179782": {
      "comment": 54931851,
      "repost": 180791177,
      "like": 76079047,
      "total": 311802075,
      "followers": 2700463
    },
    "7817162132": {
      "comment": 64799165,
      "repost": 399655603,
      "like": 83751675,
      "total": 548206443,
      "followers": 2843408
    },
    "3177765082": {
      "comment": 18454373,
      "repost": 223269181,
      "like": 53294907,
      "total": 295018461,
      "followers": 2864556
    }
  },
  "update_time": "2026-07-11 17:51:16"
}