{
  "date": "2026-06-26",
  "baseline": {
    "6353131515": {
      "comment": 46545143,
      "repost": 405902960,
      "like": 57253773,
      "total": 509701876
    },
    "7740929779": {
      "comment": 85104225,
      "repost": 646888723,
      "like": 56995047,
      "total": 788987995
    },
    "3625607515": {
      "comment": 28561016,
      "repost": 462208166,
      "like": 186245386,
      "total": 677014568
    },
    "3448351424": {
      "comment": 29796195,
      "repost": 182441382,
      "like": 51891001,
      "total": 264128578
    },
    "6320179782": {
      "comment": 53691749,
      "repost": 172471820,
      "like": 73216686,
      "total": 299380255
    },
    "7817162132": {
      "comment": 62157724,
      "repost": 387418331,
      "like": 80524009,
      "total": 530100064
    },
    "3177765082": {
      "comment": 17284622,
      "repost": 215867704,
      "like": 50517561,
      "total": 283669887
    }
  },
  "current": {
    "6353131515": {
      "comment": 46597214,
      "repost": 406927031,
      "like": 57367257,
      "total": 510891502,
      "followers": 2803689
    },
    "7740929779": {
      "comment": 85145650,
      "repost": 647375194,
      "like": 57014753,
      "total": 789535597,
      "followers": 2357970
    },
    "3625607515": {
      "comment": 28604158,
      "repost": 466057736,
      "like": 186302541,
      "total": 680964435,
      "followers": 3307309
    },
    "3448351424": {
      "comment": 29850111,
      "repost": 182567727,
      "like": 51995561,
      "total": 264413399,
      "followers": 2767976
    },
    "6320179782": {
      "comment": 53736486,
      "repost": 172863860,
      "like": 73292473,
      "total": 299892819,
      "followers": 2615581
    },
    "7817162132": {
      "comment": 62291872,
      "repost": 387965460,
      "like": 80600757,
      "total": 530858089,
      "followers": 2775735
    },
    "3177765082": {
      "comment": 17339373,
      "repost": 216196933,
      "like": 50551044,
      "total": 284087350,
      "followers": 2809354
    }
  },
  "update_time": "2026-06-26 17:20:45"
}