{
  "date": "2026-06-10",
  "baseline": {
    "6353131515": {
      "comment": 45076209,
      "repost": 390281270,
      "like": 55124339,
      "total": 490481818
    },
    "7740929779": {
      "comment": 83718755,
      "repost": 631152569,
      "like": 55518705,
      "total": 770390029
    },
    "3625607515": {
      "comment": 27258204,
      "repost": 353639352,
      "like": 173646479,
      "total": 554544035
    },
    "3448351424": {
      "comment": 28495185,
      "repost": 179519609,
      "like": 49832729,
      "total": 257847523
    },
    "6320179782": {
      "comment": 52525182,
      "repost": 164137042,
      "like": 70544363,
      "total": 287206587
    },
    "7817162132": {
      "comment": 59137943,
      "repost": 375201226,
      "like": 77131445,
      "total": 511470614
    },
    "3177765082": {
      "comment": 16184928,
      "repost": 209816015,
      "like": 48203609,
      "total": 274204552
    }
  },
  "current": {
    "6353131515": {
      "comment": 45174297,
      "repost": 391084680,
      "like": 55236033,
      "total": 491495010,
      "followers": 2770217
    },
    "7740929779": {
      "comment": 83785025,
      "repost": 632058639,
      "like": 55547926,
      "total": 771391590,
      "followers": 2345433
    },
    "3625607515": {
      "comment": 27404751,
      "repost": 361693800,
      "like": 175842394,
      "total": 564940945,
      "followers": 3245437
    },
    "3448351424": {
      "comment": 28566017,
      "repost": 179685269,
      "like": 49891699,
      "total": 258142985,
      "followers": 2720867
    },
    "6320179782": {
      "comment": 52580814,
      "repost": 164616286,
      "like": 70668923,
      "total": 287866023,
      "followers": 2556252
    },
    "7817162132": {
      "comment": 59339039,
      "repost": 375967245,
      "like": 77237157,
      "total": 512543441,
      "followers": 2733309
    },
    "3177765082": {
      "comment": 16233288,
      "repost": 210097184,
      "like": 48275703,
      "total": 274606175,
      "followers": 2765578
    }
  },
  "update_time": "2026-06-10 23:50:48"
}