{
  "date": "2026-06-26",
  "baseline": {
    "6353131515": {
      "comment": 46545143,
      "repost": 405902960,
      "like": 57253773,
      "total": 509701876
    },
    "7740929779": {
      "comment": 85104225,
      "repost": 646888723,
      "like": 56995047,
      "total": 788987995
    },
    "3625607515": {
      "comment": 28561016,
      "repost": 462208166,
      "like": 186245386,
      "total": 677014568
    },
    "3448351424": {
      "comment": 29796195,
      "repost": 182441382,
      "like": 51891001,
      "total": 264128578
    },
    "6320179782": {
      "comment": 53691749,
      "repost": 172471820,
      "like": 73216686,
      "total": 299380255
    },
    "7817162132": {
      "comment": 62157724,
      "repost": 387418331,
      "like": 80524009,
      "total": 530100064
    },
    "3177765082": {
      "comment": 17284622,
      "repost": 215867704,
      "like": 50517561,
      "total": 283669887
    }
  },
  "current": {
    "6353131515": {
      "comment": 46557676,
      "repost": 406160882,
      "like": 57285700,
      "total": 510004258,
      "followers": 2802781
    },
    "7740929779": {
      "comment": 85110332,
      "repost": 647000395,
      "like": 56996496,
      "total": 789107223,
      "followers": 2357689
    },
    "3625607515": {
      "comment": 28570596,
      "repost": 462841732,
      "like": 186252385,
      "total": 677664713,
      "followers": 3306090
    },
    "3448351424": {
      "comment": 29804867,
      "repost": 182463572,
      "like": 51911313,
      "total": 264179752,
      "followers": 2766921
    },
    "6320179782": {
      "comment": 53704222,
      "repost": 172550595,
      "like": 73229797,
      "total": 299484614,
      "followers": 2614435
    },
    "7817162132": {
      "comment": 62173820,
      "repost": 387509276,
      "like": 80529053,
      "total": 530212149,
      "followers": 2774801
    },
    "3177765082": {
      "comment": 17296228,
      "repost": 215924805,
      "like": 50525023,
      "total": 283746056,
      "followers": 2808460
    }
  },
  "update_time": "2026-06-26 03:00:59"
}