{
  "date": "2026-07-08",
  "baseline": {
    "6353131515": {
      "comment": 47377821,
      "repost": 417785615,
      "like": 58267481,
      "total": 523430917
    },
    "7740929779": {
      "comment": 85761210,
      "repost": 655693344,
      "like": 57836006,
      "total": 799290560
    },
    "3625607515": {
      "comment": 29346684,
      "repost": 524486935,
      "like": 190138910,
      "total": 743972529
    },
    "3448351424": {
      "comment": 30557023,
      "repost": 184265160,
      "like": 53343139,
      "total": 268165322
    },
    "6320179782": {
      "comment": 54540694,
      "repost": 178502130,
      "like": 75034067,
      "total": 308076891
    },
    "7817162132": {
      "comment": 64068302,
      "repost": 395959875,
      "like": 82714947,
      "total": 542743124
    },
    "3177765082": {
      "comment": 18172219,
      "repost": 221662496,
      "like": 52789053,
      "total": 292623768
    }
  },
  "current": {
    "6353131515": {
      "comment": 47391047,
      "repost": 417877628,
      "like": 58273410,
      "total": 523542085,
      "followers": 2846654
    },
    "7740929779": {
      "comment": 85766365,
      "repost": 655741402,
      "like": 57838178,
      "total": 799345945,
      "followers": 2369655
    },
    "3625607515": {
      "comment": 29351977,
      "repost": 524990511,
      "like": 190152412,
      "total": 744494900,
      "followers": 3353349
    },
    "3448351424": {
      "comment": 30561884,
      "repost": 184293921,
      "like": 53352026,
      "total": 268207831,
      "followers": 2816675
    },
    "6320179782": {
      "comment": 54543249,
      "repost": 178543721,
      "like": 75045859,
      "total": 308132829,
      "followers": 2675681
    },
    "7817162132": {
      "comment": 64082120,
      "repost": 396032190,
      "like": 82721066,
      "total": 542835376,
      "followers": 2823574
    },
    "3177765082": {
      "comment": 18178019,
      "repost": 221704712,
      "like": 52796864,
      "total": 292679595,
      "followers": 2849435
    }
  },
  "update_time": "2026-07-08 01:51:07"
}