{
  "date": "2026-07-19",
  "baseline": {
    "6353131515": {
      "comment": 48409395,
      "repost": 431405945,
      "like": 59390726,
      "total": 539206066
    },
    "7740929779": {
      "comment": 86230054,
      "repost": 664716925,
      "like": 58675303,
      "total": 809622282
    },
    "3625607515": {
      "comment": 30021933,
      "repost": 588851362,
      "like": 194000535,
      "total": 812873830
    },
    "3448351424": {
      "comment": 31028932,
      "repost": 186173925,
      "like": 54370102,
      "total": 271572959
    },
    "6320179782": {
      "comment": 55477007,
      "repost": 185003758,
      "like": 77201816,
      "total": 317682581
    },
    "7817162132": {
      "comment": 65985527,
      "repost": 405278697,
      "like": 84339649,
      "total": 555603873
    },
    "3177765082": {
      "comment": 18964234,
      "repost": 226952977,
      "like": 54666912,
      "total": 300584123
    }
  },
  "current": {
    "6353131515": {
      "comment": 48463977,
      "repost": 432309960,
      "like": 59438880,
      "total": 540212817,
      "followers": 2913338
    },
    "7740929779": {
      "comment": 86293091,
      "repost": 666757304,
      "like": 58970255,
      "total": 812020650,
      "followers": 2390913
    },
    "3625607515": {
      "comment": 30099450,
      "repost": 591568405,
      "like": 194526900,
      "total": 816194755,
      "followers": 3402973
    },
    "3448351424": {
      "comment": 31051275,
      "repost": 186269020,
      "like": 54398308,
      "total": 271718603,
      "followers": 2880443
    },
    "6320179782": {
      "comment": 55520832,
      "repost": 185459868,
      "like": 77271941,
      "total": 318252641,
      "followers": 2759033
    },
    "7817162132": {
      "comment": 66151518,
      "repost": 405839021,
      "like": 84420087,
      "total": 556410626,
      "followers": 2885296
    },
    "3177765082": {
      "comment": 19015104,
      "repost": 227370062,
      "like": 55221922,
      "total": 301607088,
      "followers": 2906696
    }
  },
  "update_time": "2026-07-19 18:01:01"
}