{
  "date": "2026-07-02",
  "baseline": {
    "6353131515": {
      "comment": 46925566,
      "repost": 411421800,
      "like": 57741012,
      "total": 516088378
    },
    "7740929779": {
      "comment": 85485058,
      "repost": 651621005,
      "like": 57557898,
      "total": 794663961
    },
    "3625607515": {
      "comment": 29000065,
      "repost": 487944433,
      "like": 189006921,
      "total": 705951419
    },
    "3448351424": {
      "comment": 30218608,
      "repost": 183428968,
      "like": 52651719,
      "total": 266299295
    },
    "6320179782": {
      "comment": 54099023,
      "repost": 175515970,
      "like": 74176818,
      "total": 303791811
    },
    "7817162132": {
      "comment": 63103675,
      "repost": 391564715,
      "like": 81873613,
      "total": 536542003
    },
    "3177765082": {
      "comment": 17737971,
      "repost": 218358999,
      "like": 51121509,
      "total": 287218479
    }
  },
  "current": {
    "6353131515": {
      "comment": 46986447,
      "repost": 412184383,
      "like": 57771638,
      "total": 516942468,
      "followers": 2830152
    },
    "7740929779": {
      "comment": 85534396,
      "repost": 652553637,
      "like": 57619709,
      "total": 795707742,
      "followers": 2363622
    },
    "3625607515": {
      "comment": 29049477,
      "repost": 493225988,
      "like": 189119595,
      "total": 711395060,
      "followers": 3333954
    },
    "3448351424": {
      "comment": 30259990,
      "repost": 183532755,
      "like": 52697781,
      "total": 266490526,
      "followers": 2792089
    },
    "6320179782": {
      "comment": 54158087,
      "repost": 176027729,
      "like": 74283748,
      "total": 304469564,
      "followers": 2645918
    },
    "7817162132": {
      "comment": 63241865,
      "repost": 392323116,
      "like": 82035851,
      "total": 537600832,
      "followers": 2799541
    },
    "3177765082": {
      "comment": 17803385,
      "repost": 218906468,
      "like": 51676462,
      "total": 288386315,
      "followers": 2829832
    }
  },
  "update_time": "2026-07-02 22:40:55"
}