{
  "date": "2026-06-26",
  "baseline": {
    "6353131515": {
      "comment": 46545143,
      "repost": 405902960,
      "like": 57253773,
      "total": 509701876
    },
    "7740929779": {
      "comment": 85104225,
      "repost": 646888723,
      "like": 56995047,
      "total": 788987995
    },
    "3625607515": {
      "comment": 28561016,
      "repost": 462208166,
      "like": 186245386,
      "total": 677014568
    },
    "3448351424": {
      "comment": 29796195,
      "repost": 182441382,
      "like": 51891001,
      "total": 264128578
    },
    "6320179782": {
      "comment": 53691749,
      "repost": 172471820,
      "like": 73216686,
      "total": 299380255
    },
    "7817162132": {
      "comment": 62157724,
      "repost": 387418331,
      "like": 80524009,
      "total": 530100064
    },
    "3177765082": {
      "comment": 17284622,
      "repost": 215867704,
      "like": 50517561,
      "total": 283669887
    }
  },
  "current": {
    "6353131515": {
      "comment": 46568951,
      "repost": 406549413,
      "like": 57311677,
      "total": 510430041,
      "followers": 2803001
    },
    "7740929779": {
      "comment": 85120317,
      "repost": 647187184,
      "like": 56999907,
      "total": 789307408,
      "followers": 2357740
    },
    "3625607515": {
      "comment": 28583682,
      "repost": 464180393,
      "like": 186257875,
      "total": 679021950,
      "followers": 3306372
    },
    "3448351424": {
      "comment": 29819010,
      "repost": 182508687,
      "like": 51938996,
      "total": 264266693,
      "followers": 2767156
    },
    "6320179782": {
      "comment": 53714991,
      "repost": 172704495,
      "like": 73225910,
      "total": 299645396,
      "followers": 2614681
    },
    "7817162132": {
      "comment": 62221676,
      "repost": 387747652,
      "like": 80537348,
      "total": 530506676,
      "followers": 2775016
    },
    "3177765082": {
      "comment": 17309373,
      "repost": 216033130,
      "like": 50522834,
      "total": 283865337,
      "followers": 2808633
    }
  },
  "update_time": "2026-06-26 10:00:57"
}