{
  "date": "2026-06-12",
  "baseline": {
    "6353131515": {
      "comment": 45241143,
      "repost": 392141850,
      "like": 55421746,
      "total": 492804739
    },
    "7740929779": {
      "comment": 83879621,
      "repost": 633129225,
      "like": 55748319,
      "total": 772757165
    },
    "3625607515": {
      "comment": 27474705,
      "repost": 368538282,
      "like": 176241362,
      "total": 572254349
    },
    "3448351424": {
      "comment": 28629615,
      "repost": 179832077,
      "like": 49949551,
      "total": 258411243
    },
    "6320179782": {
      "comment": 52654049,
      "repost": 165111896,
      "like": 70801096,
      "total": 288567041
    },
    "7817162132": {
      "comment": 59545268,
      "repost": 376696274,
      "like": 77558107,
      "total": 513799649
    },
    "3177765082": {
      "comment": 16271800,
      "repost": 210342803,
      "like": 48326083,
      "total": 274940686
    }
  },
  "current": {
    "6353131515": {
      "comment": 45261338,
      "repost": 392568585,
      "like": 55428669,
      "total": 493258592,
      "followers": 2771140
    },
    "7740929779": {
      "comment": 83899831,
      "repost": 633719799,
      "like": 55773531,
      "total": 773393161,
      "followers": 2345518
    },
    "3625607515": {
      "comment": 27496516,
      "repost": 370821316,
      "like": 176260991,
      "total": 574578823,
      "followers": 3249280
    },
    "3448351424": {
      "comment": 28645230,
      "repost": 179875587,
      "like": 49957692,
      "total": 258478509,
      "followers": 2722032
    },
    "6320179782": {
      "comment": 52670361,
      "repost": 165307973,
      "like": 70804050,
      "total": 288782384,
      "followers": 2557821
    },
    "7817162132": {
      "comment": 59633236,
      "repost": 377156261,
      "like": 77608966,
      "total": 514398463,
      "followers": 2734328
    },
    "3177765082": {
      "comment": 16282227,
      "repost": 210436512,
      "like": 48328367,
      "total": 275047106,
      "followers": 2766988
    }
  },
  "update_time": "2026-06-12 10:00:53"
}